[
  {
    "id": "bmr",
    "name": "黯月初升 (Bad Moon Rising)",
    "characterIds": [
      "grandmother",
      "sailor",
      "chambermaid",
      "exorcist",
      "innkeeper",
      "gambler",
      "gossip",
      "courtier",
      "professor",
      "minstrel",
      "tealady",
      "pacifist",
      "fool",
      "tinker",
      "moonchild",
      "goon",
      "lunatic",
      "godfather",
      "devilsadvocate",
      "assassin",
      "mastermind",
      "zombuul",
      "pukka",
      "shabaloth",
      "po"
    ]
  },
  {
    "id": "jgtm",
    "name": "金戈铁马",
    "characterIds": [
      "cn_4797c4ed",
      "fortuneteller",
      "chambermaid",
      "guide",
      "cn_3d950d5f",
      "cn_b8705a44",
      "acrobat",
      "savant",
      "facechanger",
      "cn_53209a2e",
      "fisherman",
      "brushholder",
      "drunk",
      "barber",
      "pedant",
      "mortician",
      "summoner",
      "cn_3a0e6895",
      "assassin",
      "baron",
      "cn_24b359bf",
      "nodashii",
      "imp",
      "pukka"
    ]
  },
  {
    "id": "jmtx",
    "name": "寄梦他乡",
    "characterIds": [
      "stargazer",
      "yin",
      "waiter",
      "empath",
      "dreamer",
      "guide",
      "villageidiot",
      "exorcist",
      "undertaker",
      "gossip",
      "diva",
      "banxian",
      "turncoat",
      "acrobat",
      "plaguedoctor",
      "barber",
      "lioneagle",
      "cerenovus",
      "assassin",
      "corpsewalker",
      "warden",
      "sycophant",
      "hundun",
      "kazali"
    ]
  },
  {
    "id": "jqsg",
    "name": "九泉颂歌",
    "characterIds": [
      "amnesiac",
      "yin",
      "guide",
      "firewatcher",
      "innkeeper",
      "undertaker",
      "cn_2ceeca45",
      "brushholder",
      "diva",
      "cn_e1b9ca8e",
      "cn_14acecc8",
      "minstrel",
      "mutant",
      "barber",
      "politician",
      "cn_ac14435e",
      "imperialist",
      "lioneagle",
      "marionette",
      "godfather",
      "ojo",
      "taotie",
      "po"
    ]
  },
  {
    "id": "mth",
    "name": "满堂红",
    "characterIds": [
      "cn_2ceeca45",
      "flowergirl",
      "towncrier",
      "savant",
      "cannibal",
      "gossip",
      "noble",
      "slayer",
      "gambler",
      "fisherman",
      "chef",
      "drunk",
      "recluse",
      "mortician",
      "mutant",
      "brewer",
      "godfather",
      "pit",
      "assassin",
      "sycophant",
      "lilmonsta",
      "imp"
    ]
  },
  {
    "id": "qjqm",
    "name": "曲尽其妙",
    "characterIds": [
      "stargazer",
      "grandmother",
      "slayer",
      "cn_4797c4ed",
      "brushholder",
      "chambermaid",
      "guide",
      "cn_b8705a44",
      "cn_dbf40e5f",
      "cn_3d950d5f",
      "diva",
      "nightwatchman",
      "gossip",
      "drunk",
      "recluse",
      "turncoat",
      "mortician",
      "cn_3a0e6895",
      "godfather",
      "poisoner",
      "boffin",
      "scarletwoman",
      "cn_24b359bf",
      "hundun",
      "taotie",
      "spiritofivory"
    ]
  },
  {
    "id": "qqsy",
    "name": "窃窃私语",
    "characterIds": [
      "balloonist",
      "savant",
      "amnesiac",
      "fisherman",
      "artist",
      "cannibal",
      "mutant",
      "lunatic",
      "widow",
      "goblin",
      "leviathan"
    ]
  },
  {
    "id": "ryxw",
    "name": "日月偕亡",
    "characterIds": [
      "chef",
      "investigator",
      "stargazer",
      "seamstress",
      "chambermaid",
      "guide",
      "fortuneteller",
      "empath",
      "cn_3d950d5f",
      "cn_70381678",
      "gossip",
      "savant",
      "drunk",
      "klutz",
      "recluse",
      "assassin",
      "brewer",
      "marionette",
      "scarletwoman",
      "cn_24b359bf",
      "ojo",
      "vortox",
      "nodashii"
    ]
  },
  {
    "id": "snv",
    "name": "梦殒春宵 (Sects & Violets)",
    "characterIds": [
      "clockmaker",
      "dreamer",
      "snakecharmer",
      "mathematician",
      "flowergirl",
      "towncrier",
      "oracle",
      "savant",
      "seamstress",
      "philosopher",
      "artist",
      "juggler",
      "sage",
      "mutant",
      "sweetheart",
      "barber",
      "klutz",
      "eviltwin",
      "witch",
      "cerenovus",
      "pit",
      "fanggu",
      "vigormortis",
      "nodashii",
      "vortox"
    ]
  },
  {
    "id": "ssh",
    "name": "十三行",
    "characterIds": [
      "grandmother",
      "sailor",
      "preacher",
      "guide",
      "chambermaid",
      "heshang",
      "cn_b8705a44",
      "gossip",
      "fisherman",
      "cannibal",
      "banxian",
      "goon",
      "damsel",
      "tinker",
      "acrobat",
      "devilsadvocate",
      "cn_3a0e6895",
      "poisoner",
      "godfather",
      "taotie",
      "warden",
      "imp",
      "pukka"
    ]
  },
  {
    "id": "syyl",
    "name": "山雨欲来",
    "characterIds": [
      "brushholder",
      "cn_b8705a44",
      "cn_4797c4ed",
      "cn_e1b9ca8e",
      "broker",
      "cn_dbf40e5f",
      "cn_2ceeca45",
      "cn_70381678",
      "guide",
      "cn_14acecc8",
      "cn_53209a2e",
      "cn_3d950d5f",
      "cn_b8323f61",
      "mortician",
      "cn_3a0e6895",
      "brewer",
      "cn_24b359bf",
      "cn_f68253a3"
    ]
  },
  {
    "id": "tb",
    "name": "暗流涌动 (Trouble Brewing)",
    "characterIds": [
      "washerwoman",
      "librarian",
      "investigator",
      "chef",
      "empath",
      "fortuneteller",
      "undertaker",
      "monk",
      "ravenkeeper",
      "virgin",
      "slayer",
      "soldier",
      "mayor",
      "butler",
      "drunk",
      "recluse",
      "saint",
      "poisoner",
      "spy",
      "scarletwoman",
      "baron",
      "imp"
    ]
  },
  {
    "id": "wdcs",
    "name": "华灯初上",
    "characterIds": [
      "banxian",
      "facechanger",
      "firewatcher",
      "waiter",
      "diva",
      "heshang",
      "brocadier",
      "herbdoctor",
      "stargazer",
      "enlightenedone",
      "actor",
      "rascal",
      "yin",
      "turncoat",
      "cn_ac14435e",
      "ambassador",
      "pedant",
      "corpsewalker",
      "vixen",
      "imperialist",
      "bugkeeper",
      "hundun",
      "qiongqi",
      "taotie",
      "taowu"
    ]
  },
  {
    "id": "wsyy",
    "name": "无上愉悦",
    "characterIds": [
      "clockmaker",
      "investigator",
      "empath",
      "chambermaid",
      "artist",
      "sage",
      "drunk",
      "klutz",
      "scarletwoman",
      "baron",
      "imp"
    ]
  },
  {
    "id": "wycs",
    "name": "雾隐苍生",
    "characterIds": [
      "empath",
      "cn_2ceeca45",
      "highpriestess",
      "cn_3d950d5f",
      "cn_53209a2e",
      "herbdoctor",
      "enlightenedone",
      "noble",
      "dreamer",
      "cannibal",
      "barber",
      "mutant",
      "mortician",
      "plaguedoctor",
      "pit",
      "mezepheles",
      "lioneagle",
      "harpy",
      "imp",
      "hundun",
      "kazali",
      "vortox"
    ]
  },
  {
    "id": "yhjm",
    "name": "移花接木",
    "characterIds": [
      "herbdoctor",
      "heshang",
      "chambermaid",
      "fortuneteller",
      "gambler",
      "villageidiot",
      "nightwatchman",
      "gossip",
      "banxian",
      "cannibal",
      "mathematician",
      "broker",
      "guide",
      "lunatic",
      "goon",
      "ambassador",
      "cn_b8323f61",
      "godfather",
      "marionette",
      "harpy",
      "lioneagle",
      "taotie",
      "hundun",
      "pukka",
      "warden"
    ]
  },
  {
    "id": "zgqm",
    "name": "子规泣鸣",
    "characterIds": [
      "chef",
      "yin",
      "brushholder",
      "cn_2ceeca45",
      "undertaker",
      "cn_53209a2e",
      "cn_70381678",
      "cn_4797c4ed",
      "empath",
      "fortuneteller",
      "chambermaid",
      "recluse",
      "drunk",
      "plaguedoctor",
      "godfather",
      "lioneagle",
      "harpy",
      "marionette",
      "warden",
      "cn_f68253a3",
      "lilmonsta"
    ]
  }
]
